setup.py
pyvision.egg-info/PKG-INFO
pyvision.egg-info/SOURCES.txt
pyvision.egg-info/dependency_links.txt
pyvision.egg-info/top_level.txt
vision/__init__.py
vision/annotations.c
vision/annotations.pxd
vision/annotations.pyx
vision/convolution.c
vision/convolution.pyx
vision/features.c
vision/features.pyx
vision/flickr.py
vision/model.c
vision/model.pyx
vision/svm.cpp
vision/svm.pyx
vision/toymaker.py
vision/visualize.py
vision/ffmpeg/__init__.py
vision/ffmpeg/extract.cpp
vision/ffmpeg/extract.pyx
vision/track/__init__.py
vision/track/alearn.c
vision/track/alearn.pyx
vision/track/interpolation.py
vision/track/standard.c
vision/track/standard.pyx
vision/track/util.py